README.md
setup.py
src/jedi_bundle/__init__.py
src/jedi_bundle/clone_jedi_bundle.py
src/jedi_bundle/configure_jedi_bundle.py
src/jedi_bundle/make_jedi_bundle.py
src/jedi_bundle/bin/__init__.py
src/jedi_bundle/bin/jedi_bundle.py
src/jedi_bundle/config/__init__.py
src/jedi_bundle/config/config.py
src/jedi_bundle/utils/__init__.py
src/jedi_bundle/utils/config.py
src/jedi_bundle/utils/file_system.py
src/jedi_bundle/utils/git.py
src/jedi_bundle/utils/logger.py
src/jedi_bundle/utils/yaml.py
src/jedibundle.egg-info/PKG-INFO
src/jedibundle.egg-info/SOURCES.txt
src/jedibundle.egg-info/dependency_links.txt
src/jedibundle.egg-info/entry_points.txt
src/jedibundle.egg-info/requires.txt
src/jedibundle.egg-info/top_level.txt