Metadata-Version: 2.1
Name: jedibundle
Version: 1.0.5
Summary: Tools for installing JEDI code
Home-page: https://github.com/geos-esm/jedi_bundle
Author: NASA Global Modeling and Assimilation Office
License: UNKNOWN
Platform: UNKNOWN
Classifier: Development Status :: 1 - Planning
Classifier: Environment :: Console
Classifier: Intended Audience :: Science/Research
Classifier: Programming Language :: Python :: 3 :: Only
Classifier: License :: OSI Approved :: Apache Software License
Classifier: Natural Language :: English
Classifier: Operating System :: OS Independent
Requires-Python: >=3.6
